{
  "main": {
    "id": "985acf686645fd7e",
    "type": "split",
    "children": [
      {
        "id": "eb11952cbafbcec7",
        "type": "tabs",
        "children": [
          {
            "id": "b6e1cef4f8fcdb59",
            "type": "leaf",
            "state": {
              "type": "markdown",
              "state": {
                "file": "jenkins.md",
                "mode": "source",
                "source": false
              }
            }
          }
        ]
      }
    ],
    "direction": "vertical"
  },
  "left": {
    "id": "cdb595ed222eecf5",
    "type": "split",
    "children": [
      {
        "id": "7246ff89f495bfe0",
        "type": "tabs",
        "children": [
          {
            "id": "1ff50df533d5514f",
            "type": "leaf",
            "state": {
              "type": "file-explorer",
              "state": {
                "sortOrder": "alphabetical"
              }
            }
          },
          {
            "id": "53545c78f0a1b254",
            "type": "leaf",
            "state": {
              "type": "search",
              "state": {
                "query": "",
                "matchingCase": false,
                "explainSearch": false,
                "collapseAll": false,
                "extraContext": false,
                "sortOrder": "alphabetical"
              }
            }
          },
          {
            "id": "ac2c91b9086aa919",
            "type": "leaf",
            "state": {
              "type": "starred",
              "state": {}
            }
          }
        ]
      }
    ],
    "direction": "horizontal",
    "width": 300
  },
  "right": {
    "id": "65d2b5b2bb98de98",
    "type": "split",
    "children": [
      {
        "id": "51fefd9463c06c93",
        "type": "tabs",
        "children": [
          {
            "id": "4b8f31f06924df5d",
            "type": "leaf",
            "state": {
              "type": "backlink",
              "state": {
                "file": "jenkins.md",
                "collapseAll": false,
                "extraContext": false,
                "sortOrder": "alphabetical",
                "showSearch": false,
                "searchQuery": "",
                "backlinkCollapsed": false,
                "unlinkedCollapsed": true
              }
            }
          },
          {
            "id": "1cd0d004ce7e9923",
            "type": "leaf",
            "state": {
              "type": "outgoing-link",
              "state": {
                "file": "jenkins.md",
                "linksCollapsed": false,
                "unlinkedCollapsed": true
              }
            }
          },
          {
            "id": "21ca54b0cf4ce51f",
            "type": "leaf",
            "state": {
              "type": "tag",
              "state": {
                "sortOrder": "frequency",
                "useHierarchy": true
              }
            }
          },
          {
            "id": "01b41725714fec9a",
            "type": "leaf",
            "state": {
              "type": "outline",
              "state": {
                "file": "jenkins.md"
              }
            }
          }
        ]
      }
    ],
    "direction": "horizontal",
    "width": 300,
    "collapsed": true
  },
  "left-ribbon": {
    "hiddenItems": {
      "switcher:打开快速切换": false,
      "graph:查看关系图谱": false,
      "canvas:Create new canvas": false,
      "daily-notes:打开/创建今天的日记": false,
      "templates:插入模板": false,
      "command-palette:打开命令面板": false
    }
  },
  "active": "b6e1cef4f8fcdb59",
  "lastOpenFiles": [
    "auto/定时任务.md",
    "jenkins.md",
    "Pasted image 20230207104319.png",
    "Jenkins.md",
    "Pasted image 20230207104020.png"
  ]
}